{
  "markers":[
   {
      "markerType":"Mokoko",
      "enabled":true,
      "allowSidebar":true,
      "layerID":"layer_mokoko",
      "data":[
         {
            "coordinates":[
               -52.375, 153.5
            ],
            "id":"mokoko_0",
            "popupTitle":"Mokoko Seed",
            "popupContent":"",
            "popupMedia":"",
            "tooltip":"",
            "tooltipDirection":"right"
         },
         {
            "coordinates":[
               -103.75, 174.875
            ],
            "id":"mokoko_1",
            "popupTitle":"Mokoko Seed",
            "popupContent":"",
            "popupMedia":"",
            "tooltip":"",
            "tooltipDirection":"right"
         },
         {
            "coordinates":[
               -122.875, 180.875
            ],
            "id":"mokoko_2",
            "popupTitle":"Mokoko Seed",
            "popupContent":"",
            "popupMedia":"",
            "tooltip":"",
            "tooltipDirection":"right"
         }
      ]
     },
     {
        "markerType":"Portal",
        "enabled":true,
        "allowSidebar":false,
        "layerID":"layer_portal",
        "data":[
           {
              "coordinates":[
               -255.5, 149.25
              ],
              "id":"portal_0",
              "destinationID":"overworld",
              "tooltip":"Open Seas",
              "tooltipDirection":"bottom"
           }
        ]
     }
  ]
}